mlpyqtgraph/__init__.py
mlpyqtgraph/axes.py
mlpyqtgraph/colors.py
mlpyqtgraph/config.py
mlpyqtgraph/grid_axes.py
mlpyqtgraph/ml_functions.py
mlpyqtgraph/windows.py
mlpyqtgraph/workers.py
mlpyqtgraph/utils/GLSurfacePlotItem.py
mlpyqtgraph/utils/GLTextItem.py
mlpyqtgraph/utils/ticklabels.py
mlpyqtgraph-0.9.1.dist-info/licenses/LICENSE
mlpyqtgraph-0.9.1.dist-info/METADATA
mlpyqtgraph-0.9.1.dist-info/WHEEL
mlpyqtgraph-0.9.1.dist-info/top_level.txt
mlpyqtgraph-0.9.1.dist-info/RECORD
