Metadata-Version: 2.4
Name: mlpyqtgraph
Version: 0.9.1
Summary: Matplotlib like plotting with pyqtgraph in python
Author-email: Sietze van Buuren <s.van.buuren@gmail.com>
License: Copyright 2024 Sietze van Buuren <s.van.buuren@gmail.com>
Project-URL: Homepage, https://github.com/swvanbuuren/mlpyqtgraph
Classifier: Programming Language :: Python :: 3.12
Classifier: License :: OSI Approved :: MIT License
Classifier: Operating System :: OS Independent
Requires-Python: >=3.12
License-File: LICENSE
Requires-Dist: pyqtgraph==0.14.0
Requires-Dist: pqthreads==0.6.1
Requires-Dist: pyopengl==3.1.10
Dynamic: license-file
